{"address1": "Los Angeles CA 90071", "address2": "333 S Hope St - 55th Fl (MICG)", "address3": "Capital Income Builder Inc", "phone": "213-486-9200", "longBusinessSummary": "The fund normally will invest at least 90% of its assets in income-producing securities (with at least 50% of its assets in common stocks and other equity securities). It invests primarily in a broad range of income-producing securities, including common stocks and bonds. In seeking to provide the investors with a level of current income that exceeds the average yield on U.S. stocks, the fund generally looks to the average yield on stocks of companies listed on the S&P 500 Index.", "companyOfficers": []}