{"address1": "9350 Excelsior Boulevard", "address2": "Suite 700", "city": "Hopkins", "state": "MN", "zip": "55343", "country": "United States", "phone": "952 912 3444", "website": "https://www.digi.com", "industry": "Communication Equipment", "sector": "Technology", "longBusinessSummary": "Digi International Inc. provides business and mission-critical Internet of Things (IoT) products, services, and solutions in the United States and internationally. The company operates in two segments, IoT Products & Services and IoT Solutions. It offers cellular routers for mission-critical wireless connectivity; cellular modules to embed cellular communications abilities into the products to deploy and manage intelligent and secure cellular connected products; console servers to provide secure and remote access to network equipment in data centers and at edge locations; and radio frequency products, including embedded wireless modules, off-the-shelf gateways, modems, and adapters under the Digi XBee brand. The company provides embedded system products under the Digi Connect, ConnectCore, and Rabbit brands; and infrastructure management products, comprising of serial servers, which offers serial port-to-Ethernet integration of devices into wired Ethernet networks; and universal serial bus solutions. In addition, it offers Digi Remote Manager and Lighthouse, a recurring revenue cloud-based service that provides a secure environment for customers to manage their connected device deployment and network devices; and SmartSense by Digi for monitoring wirelessly the temperature of food and other perishable or sensitive goods, monitor facilities or pharmacies by tracking the completion of operating tasks by employees, as well as quality control and incident management for food service, healthcare, and transportation/logistics industries. Further, the company provides professional services, such as site planning, implementation management, application development, and customer training; data plan subscriptions; and enhanced technical support services, as well as Digi Wireless Design Services. Digi International Inc. was incorporated in 1985 and is headquartered in Hopkins, Minnesota.", "fullTimeEmployees": 790, "companyOfficers": [{"maxAge": 1, "name": "Mr. Ronald E. Konezny", "age": 54, "title": "Pres, CEO & Director", "yearBorn": 1968, "fiscalYear": 2022, "totalPay": {"raw": 1628360, "fmt": "1.63M", "longFmt": "1,628,360"}, "exercisedValue": {"raw": 8798813, "fmt": "8.8M", "longFmt": "8,798,813"}, "unexercisedValue": {"raw": 4919502, "fmt": "4.92M", "longFmt": "4,919,502"}}, {"maxAge": 1, "name": "Mr. James J. Loch", "age": 49, "title": "Exec. VP, CFO & Treasurer", "yearBorn": 1973, "fiscalYear": 2022, "totalPay": {"raw": 722533, "fmt": "722.53k", "longFmt": "722,533"}, "exercisedValue": {"raw": 0, "fmt": null, "longFmt": "0"}, "unexercisedValue": {"raw": 2351797, "fmt": "2.35M", "longFmt": "2,351,797"}}, {"maxAge": 1, "name": "Ms. Radha  Chavali", "age": 49, "title": "Sr. VP & Chief Information Officer", "yearBorn": 1973, "fiscalYear": 2022, "totalPay": {"raw": 375759, "fmt": "375.76k", "longFmt": "375,759"}, "exercisedValue": {"raw": 0, "fmt": null, "longFmt": "0"}, "unexercisedValue": {"raw": 0, "fmt": null, "longFmt": "0"}}, {"maxAge": 1, "name": "Mr. David H. Sampsell", "age": 54, "title": "Exec. VP of Corp. Devel., Gen. Counsel & Corp. Sec.", "yearBorn": 1968, "fiscalYear": 2022, "totalPay": {"raw": 617630, "fmt": "617.63k", "longFmt": "617,630"}, "exercisedValue": {"raw": 1567801, "fmt": "1.57M", "longFmt": "1,567,801"}, "unexercisedValue": {"raw": 958075, "fmt": "958.08k", "longFmt": "958,075"}}, {"maxAge": 1, "name": "Mr. Terrence G. Schneider", "age": 56, "title": "Sr. VP of Supply Chain Management", "yearBorn": 1966, "fiscalYear": 2022, "totalPay": {"raw": 484797, "fmt": "484.8k", "longFmt": "484,797"}, "exercisedValue": {"raw": 106000, "fmt": "106k", "longFmt": "106,000"}, "unexercisedValue": {"raw": 888748, "fmt": "888.75k", "longFmt": "888,748"}}, {"maxAge": 1, "name": "Mr. Brian G. Ballenger", "title": "VP of Fin. & Accounting", "fiscalYear": 2019, "exercisedValue": {"raw": 0, "fmt": null, "longFmt": "0"}, "unexercisedValue": {"raw": 0, "fmt": null, "longFmt": "0"}}, {"maxAge": 1, "name": "Mr. Steve  Ericson", "title": "Sr. VP & GM of OEM Solutions", "exercisedValue": {"raw": 0, "fmt": null, "longFmt": "0"}, "unexercisedValue": {"raw": 0, "fmt": null, "longFmt": "0"}}, {"maxAge": 1, "name": "Mr. Justin O. Schmid", "title": "Sr. VP & GM of Managed Solutions", "exercisedValue": {"raw": 0, "fmt": null, "longFmt": "0"}, "unexercisedValue": {"raw": 0, "fmt": null, "longFmt": "0"}}, {"maxAge": 1, "name": "Mr. Gary  Marks", "age": 64, "title": "Sr. VP & GM of Opengear", "yearBorn": 1958, "exercisedValue": {"raw": 0, "fmt": null, "longFmt": "0"}, "unexercisedValue": {"raw": 0, "fmt": null, "longFmt": "0"}}, {"maxAge": 1, "name": "Mr. Brian  Kirkendall", "title": "Sr. VP & GM of Infrastructure Management", "exercisedValue": {"raw": 0, "fmt": null, "longFmt": "0"}, "unexercisedValue": {"raw": 0, "fmt": null, "longFmt": "0"}}], "auditRisk": 6, "boardRisk": 3, "compensationRisk": 2, "shareHolderRightsRisk": 5, "overallRisk": 3, "governanceEpochDate": 1680307200, "compensationAsOfEpochDate": 1672444800}