{"address1": "Nine Greenway Plaza", "address2": "Suite 1300", "city": "Houston", "state": "TX", "zip": "77046", "country": "United States", "phone": "713 842 9050", "website": "https://www.magnoliaoilgas.com", "industry": "Oil & Gas E&P", "sector": "Energy", "longBusinessSummary": "Magnolia Oil & Gas Corporation engages in the acquisition, development, exploration, and production of oil, natural gas, and natural gas liquids reserves in the United States. Its properties are located primarily in Karnes County and the Giddings area in South Texas principally comprising the Eagle Ford Shale and the Austin Chalk formation. The company was incorporated in 2017 and is headquartered in Houston, Texas.", "fullTimeEmployees": 213, "companyOfficers": [{"maxAge": 1, "name": "Mr. Christopher G. Stavros", "age": 59, "title": "Pres, CEO & Director", "yearBorn": 1963, "fiscalYear": 2022, "totalPay": {"raw": 1664969, "fmt": "1.66M", "longFmt": "1,664,969"}, "exercisedValue": {"raw": 0, "fmt": null, "longFmt": "0"}, "unexercisedValue": {"raw": 0, "fmt": null, "longFmt": "0"}}, {"maxAge": 1, "name": "Mr. Brian Michael Corales CPA", "age": 42, "title": "Sr. VP, CFO and Principal Accounting & Financial Officer", "yearBorn": 1980, "fiscalYear": 2022, "totalPay": {"raw": 708741, "fmt": "708.74k", "longFmt": "708,741"}, "exercisedValue": {"raw": 0, "fmt": null, "longFmt": "0"}, "unexercisedValue": {"raw": 0, "fmt": null, "longFmt": "0"}}, {"maxAge": 1, "name": "Mr. Steve  F. Millican", "age": 46, "title": "Sr. VP of Operations", "yearBorn": 1976, "fiscalYear": 2022, "totalPay": {"raw": 792835, "fmt": "792.84k", "longFmt": "792,835"}, "exercisedValue": {"raw": 0, "fmt": null, "longFmt": "0"}, "unexercisedValue": {"raw": 0, "fmt": null, "longFmt": "0"}}, {"maxAge": 1, "name": "Mr. Timothy D. Yang", "age": 50, "title": "Exec. VP, Gen. Counsel, Corp. Sec. & Land", "yearBorn": 1972, "fiscalYear": 2022, "totalPay": {"raw": 1173538, "fmt": "1.17M", "longFmt": "1,173,538"}, "exercisedValue": {"raw": 0, "fmt": null, "longFmt": "0"}, "unexercisedValue": {"raw": 0, "fmt": null, "longFmt": "0"}}, {"maxAge": 1, "name": "Jim  Johnson", "title": "VP of Fin., IR & Treasurer", "exercisedValue": {"raw": 0, "fmt": null, "longFmt": "0"}, "unexercisedValue": {"raw": 0, "fmt": null, "longFmt": "0"}}], "auditRisk": 7, "boardRisk": 1, "compensationRisk": 1, "shareHolderRightsRisk": 4, "overallRisk": 2, "governanceEpochDate": 1680307200, "compensationAsOfEpochDate": 1672444800}