{"address1": "One Valero Way", "city": "San Antonio", "state": "TX", "zip": "78249", "country": "United States", "phone": "210 345 2000", "website": "https://www.valero.com", "industry": "Oil & Gas Refining & Marketing", "sector": "Energy", "longBusinessSummary": "Valero Energy Corporation manufactures, markets, and sells transportation fuels and petrochemical products in the United States, Canada, the United Kingdom, Ireland, Latin America, and internationally. It operates through three segments: Refining, Renewable Diesel, and Ethanol. The company produces California Reformulated Gasoline Blendstock for Oxygenate Blending and Conventional Blendstock for Oxygenate Blending gasolines, CARB diesel, diesel, jet fuel, and asphalt; aromatics; and sulfur crude oils. It sells its refined products through wholesale rack and bulk markets; and through approximately outlets under the Valero, Beacon, Diamond Shamrock, Shamrock, Ultramar, and Texaco brands. The company also produces and sells ethanol, dry distiller grains, syrup, and inedible corn oil primarily to animal feed customers. In addition, it owns and operates crude oil and refined petroleum products pipelines, terminals, tanks, marine docks, truck rack bays, and other logistics assets; and owns and operates a plant that processes animal fats, used cooking oils, and inedible distillers corn oils. The company was formerly known as Valero Refining and Marketing Company and changed its name to Valero Energy Corporation in August 1997. Valero Energy Corporation was founded in 1980 and is headquartered in San Antonio, Texas.", "fullTimeEmployees": 9716, "companyOfficers": [{"maxAge": 1, "name": "Mr. Joseph W. Gorder", "age": 65, "title": "Chairman & CEO", "yearBorn": 1957, "fiscalYear": 2022, "totalPay": {"raw": 7781849, "fmt": "7.78M", "longFmt": "7,781,849"}, "exercisedValue": {"raw": 3744665, "fmt": "3.74M", "longFmt": "3,744,665"}, "unexercisedValue": {"raw": 6200289, "fmt": "6.2M", "longFmt": "6,200,289"}}, {"maxAge": 1, "name": "Mr. R. Lane Riggs", "age": 56, "title": "Pres & COO", "yearBorn": 1966, "fiscalYear": 2022, "totalPay": {"raw": 3378714, "fmt": "3.38M", "longFmt": "3,378,714"}, "exercisedValue": {"raw": 221444, "fmt": "221.44k", "longFmt": "221,444"}, "unexercisedValue": {"raw": 0, "fmt": null, "longFmt": "0"}}, {"maxAge": 1, "name": "Mr. Jason W. Fraser", "age": 53, "title": "Exec. VP & CFO", "yearBorn": 1969, "fiscalYear": 2022, "totalPay": {"raw": 2737389, "fmt": "2.74M", "longFmt": "2,737,389"}, "exercisedValue": {"raw": 0, "fmt": null, "longFmt": "0"}, "unexercisedValue": {"raw": 0, "fmt": null, "longFmt": "0"}}, {"maxAge": 1, "name": "Ms. Cheryl L. Thomas", "age": 60, "title": "Sr. VP & CTO", "yearBorn": 1962, "fiscalYear": 2022, "totalPay": {"raw": 1892733, "fmt": "1.89M", "longFmt": "1,892,733"}, "exercisedValue": {"raw": 0, "fmt": null, "longFmt": "0"}, "unexercisedValue": {"raw": 0, "fmt": null, "longFmt": "0"}}, {"maxAge": 1, "name": "Mr. Gary K. Simmons", "age": 57, "title": "Exec. VP & Chief Commercial Officer", "yearBorn": 1965, "fiscalYear": 2022, "totalPay": {"raw": 2308480, "fmt": "2.31M", "longFmt": "2,308,480"}, "exercisedValue": {"raw": 151533, "fmt": "151.53k", "longFmt": "151,533"}, "unexercisedValue": {"raw": 0, "fmt": null, "longFmt": "0"}}, {"maxAge": 1, "name": "Mr. Lawrence Mark Schmeltekopf", "age": 58, "title": "Chief Accounting Officer & Sr. VP", "yearBorn": 1964, "exercisedValue": {"raw": 0, "fmt": null, "longFmt": "0"}, "unexercisedValue": {"raw": 0, "fmt": null, "longFmt": "0"}}, {"maxAge": 1, "name": "Mr. Homer  Bhullar", "title": "VP of Investor Relations & Fin.", "exercisedValue": {"raw": 0, "fmt": null, "longFmt": "0"}, "unexercisedValue": {"raw": 0, "fmt": null, "longFmt": "0"}}, {"maxAge": 1, "name": "Mr. J. Stephen Gilbert", "title": "Disclosure & Compliance Officer and Sec.", "exercisedValue": {"raw": 0, "fmt": null, "longFmt": "0"}, "unexercisedValue": {"raw": 0, "fmt": null, "longFmt": "0"}}, {"maxAge": 1, "name": "Mr. Richard Joe Walsh", "age": 56, "title": "Sr. VP, Gen. Counsel & Sec.", "yearBorn": 1966, "exercisedValue": {"raw": 0, "fmt": null, "longFmt": "0"}, "unexercisedValue": {"raw": 0, "fmt": null, "longFmt": "0"}}, {"maxAge": 1, "name": "Lillian  Riojas", "title": "Exec. Director of Media Relations & Communications", "exercisedValue": {"raw": 0, "fmt": null, "longFmt": "0"}, "unexercisedValue": {"raw": 0, "fmt": null, "longFmt": "0"}}], "auditRisk": 2, "boardRisk": 6, "compensationRisk": 10, "shareHolderRightsRisk": 7, "overallRisk": 8, "governanceEpochDate": 1680307200, "compensationAsOfEpochDate": 1672444800}