{"address1": "200 South Wacker Drive", "address2": "Suite 2100", "city": "Chicago", "state": "IL", "zip": "60606", "country": "United States", "phone": "312 489 5800", "website": "https://www.coeur.com", "industry": "Gold", "sector": "Basic Materials", "longBusinessSummary": "Coeur Mining, Inc. explores for precious metals in the United States, Canada, and Mexico. It primarily explores for gold, silver, zinc, and lead properties. The company holds 100% interests in the Palmarejo gold and silver mine covering an area of approximately 67,279 net acres located in the State of Chihuahua in Northern Mexico; the Rochester silver and gold mine that covers an area of approximately 43,441net acres situated in northwestern Nevada; the Kensington gold mine comprising 3,972 net acres located to the north of Juneau, Alaska; the Wharf gold mine covering an area of approximately 3,243 net acres situated in the northern Black Hills of western South Dakota; and the Silvertip silver-zinc-lead mine comprising 97,298 net acres located in northern British Columbia, Canada. Further, it markets and sells its concentrates to third-party customers, smelters, under off-take agreements. The company was formerly known as Coeur d'Alene Mines Corporation and changed its name to Coeur Mining, Inc. in May 2013. Coeur Mining, Inc. was incorporated in 1928 and is headquartered in Chicago, Illinois.", "fullTimeEmployees": 2107, "companyOfficers": [{"maxAge": 1, "name": "Mr. Mitchell J. Krebs", "age": 50, "title": "Pres, CEO & Director", "yearBorn": 1972, "fiscalYear": 2022, "totalPay": {"raw": 1860442, "fmt": "1.86M", "longFmt": "1,860,442"}, "exercisedValue": {"raw": 0, "fmt": null, "longFmt": "0"}, "unexercisedValue": {"raw": 0, "fmt": null, "longFmt": "0"}}, {"maxAge": 1, "name": "Mr. Thomas S. Whelan", "age": 52, "title": "Sr. VP & CFO", "yearBorn": 1970, "fiscalYear": 2022, "totalPay": {"raw": 866742, "fmt": "866.74k", "longFmt": "866,742"}, "exercisedValue": {"raw": 0, "fmt": null, "longFmt": "0"}, "unexercisedValue": {"raw": 0, "fmt": null, "longFmt": "0"}}, {"maxAge": 1, "name": "Mr. Michael  Routledge", "age": 51, "title": "Sr. VP & COO", "yearBorn": 1971, "fiscalYear": 2022, "totalPay": {"raw": 1026285, "fmt": "1.03M", "longFmt": "1,026,285"}, "exercisedValue": {"raw": 0, "fmt": null, "longFmt": "0"}, "unexercisedValue": {"raw": 0, "fmt": null, "longFmt": "0"}}, {"maxAge": 1, "name": "Mr. Casey M. Nault", "age": 50, "title": "Sr. VP, Gen. Counsel, Company Sec. & Chief ESG Officer", "yearBorn": 1972, "fiscalYear": 2022, "totalPay": {"raw": 805609, "fmt": "805.61k", "longFmt": "805,609"}, "exercisedValue": {"raw": 0, "fmt": null, "longFmt": "0"}, "unexercisedValue": {"raw": 0, "fmt": null, "longFmt": "0"}}, {"maxAge": 1, "name": "Ms. Emilie C. Schouten", "age": 43, "title": "Sr. VP of HR", "yearBorn": 1979, "fiscalYear": 2022, "totalPay": {"raw": 668541, "fmt": "668.54k", "longFmt": "668,541"}, "exercisedValue": {"raw": 0, "fmt": null, "longFmt": "0"}, "unexercisedValue": {"raw": 0, "fmt": null, "longFmt": "0"}}, {"maxAge": 1, "name": "Mr. Kenneth J. Watkinson", "age": 53, "title": "VP, Corp. Controller & Chief Accounting Officer", "yearBorn": 1969, "exercisedValue": {"raw": 0, "fmt": null, "longFmt": "0"}, "unexercisedValue": {"raw": 0, "fmt": null, "longFmt": "0"}}, {"maxAge": 1, "name": "Mr. Jeffrey  Wilhoit", "title": "Director of Investor Relations", "exercisedValue": {"raw": 0, "fmt": null, "longFmt": "0"}, "unexercisedValue": {"raw": 0, "fmt": null, "longFmt": "0"}}, {"maxAge": 1, "name": "Ms. Robyn G. Koyner", "title": "VP, Deputy Gen. Counsel & Chief Compliance Officer", "exercisedValue": {"raw": 0, "fmt": null, "longFmt": "0"}, "unexercisedValue": {"raw": 0, "fmt": null, "longFmt": "0"}}, {"maxAge": 1, "name": "Mr. Alim  Visram", "title": "VP of Corp. Devel.", "exercisedValue": {"raw": 0, "fmt": null, "longFmt": "0"}, "unexercisedValue": {"raw": 0, "fmt": null, "longFmt": "0"}}, {"maxAge": 1, "name": "Ms. Aoife Mairead McGrath B.Sc., M.AIG., M.Sc.", "age": 45, "title": "Sr. VP of Exploration", "yearBorn": 1977, "exercisedValue": {"raw": 0, "fmt": null, "longFmt": "0"}, "unexercisedValue": {"raw": 0, "fmt": null, "longFmt": "0"}}], "auditRisk": 2, "boardRisk": 1, "compensationRisk": 1, "shareHolderRightsRisk": 1, "overallRisk": 1, "governanceEpochDate": 1680307200, "compensationAsOfEpochDate": 1672444800}