{"address1": "Valley Forge PA 19482", "address2": "P.O. Box 2600, V26", "address3": "Vangurd Fenway Funds", "phone": "6106691000", "longBusinessSummary": "The fund invests in stocks that its advisor believes offer a good balance between reasonable valuations and attractive growth prospects relative to their peers. Stocks selected for the fund typically have earnings growth potential that, in the advisor's view, is not reflected in their current market prices. It can invest in stocks across all industry sectors and market capitalizations.", "companyOfficers": []}