{"companyOfficers": [], "twitter": "\"https://twitter.com/tusdio\"", "name": "TrueUSD", "startDate": "2018-03-06", "description": "TrueUSD (TUSD) is a cryptocurrency and operates on the Ethereum platform. TrueUSD has a current supply of 2,029,653,245.6799998 with 2,090,226,269.4599998 in circulation. The last known price of TrueUSD is 1.0002378 USD and is up 0.01 over the last 24 hours. It is currently trading on 353 active market(s) with $631,545,418.20 traded over the last 24 hours. More information can be found at https://tusd.io/."}